CardStacks/__init__.py
CardStacks-0.1.3.dist-info/LICENSE
CardStacks-0.1.3.dist-info/METADATA
CardStacks-0.1.3.dist-info/WHEEL
CardStacks-0.1.3.dist-info/top_level.txt
CardStacks-0.1.3.dist-info/RECORD
