Metadata-Version: 2.1
Name: CardStacks
Version: 0.1.3
Summary: A simple library for creating and manipulating stacks of cards.
Home-page: https://github.com/SpeedyGo55/CardStacks
Author: SpeedyGo55
Author-email: SpeedyGo55@outlook.com
License: GPLv3
Project-URL: Bug Reports, https://github.com/SpeedyGo55/CardStacks/issues
Project-URL: Source, https://github.com/SpeedyGo55/CardStacks
Keywords: cards cardstacks cardstack cardstackslib cardstackslibrary cardstackslibrarypython
Classifier: Development Status :: 3 - Alpha
Classifier: Intended Audience :: Developers
Classifier: Topic :: Games/Entertainment :: Board Games
Classifier: License :: OSI Approved :: GNU General Public License v3 (GPLv3)
Classifier: Programming Language :: Python :: 3
Requires-Python: >=3
License-File: LICENSE
